[
{"id": "147323", "title": ["VIRUS: D\u00cdNH TH\u00cdNH L\u00c0 Y\u00caU"], "age_limit": ["T13"], "movie_type": ["Ph\u1ee5 \u0111\u1ec1"], "format": ["2D"], "genre": ["Drama"], "image_url": "https://www.bhdstar.vn/wp-content/uploads/2025/05/referenceSchemeHeadOfficeallowPlaceHoldertrueheight700ldapp-17.jpg", "movie_url": "https://www.bhdstar.vn/phim/virus-dinh-thinh-la-yeu/"},
{"id": "146520", "title": ["MY LOVE WILL MAKE YOU DISAPPEAR: Y\u00caU EM EM C\u1ea2M \u01a0N"], "age_limit": ["T16"], "movie_type": ["Ph\u1ee5 \u0111\u1ec1"], "format": ["2D"], "genre": ["Romance"], "image_url": "https://www.bhdstar.vn/wp-content/uploads/2025/05/referenceSchemeHeadOfficeallowPlaceHoldertrueheight700ldapp-8.png", "movie_url": "https://www.bhdstar.vn/phim/my-love-will-make-you-disappear/"},
{"id": "143146", "title": ["SINNERS: T\u1ed8I \u0110\u1ed2"], "age_limit": ["T18"], "movie_type": ["Ph\u1ee5 \u0111\u1ec1"], "format": ["2D"], "genre": ["Horror"], "image_url": "https://www.bhdstar.vn/wp-content/uploads/2025/05/referenceSchemeHeadOfficeallowPlaceHoldertrueheight700ldapp-2.jpg", "movie_url": "https://www.bhdstar.vn/phim/sinners-toi-do/"},
{"id": "146508", "title": ["BALLERINA: T\u1eea V\u0168 TR\u1ee4 JOHN WICK"], "age_limit": ["TBC"], "movie_type": ["Ph\u1ee5 \u0111\u1ec1"], "format": ["2D"], "genre": ["Action"], "image_url": "https://www.bhdstar.vn/wp-content/uploads/2025/05/rtrueheight700ldapp-13.jpg", "movie_url": "https://www.bhdstar.vn/phim/ballerina-tu-vu-tru-john-wick/"},
{"id": "144778", "title": ["D\u1ebe M\u00c8N: CU\u1ed8C PHI\u00caU L\u01afU T\u1edaI X\u00d3M L\u1ea6Y L\u1ed8I"], "age_limit": ["P"], "movie_type": ["Ph\u1ee5 \u0111\u1ec1/L\u1ed3ng ti\u1ebfng"], "format": ["2D"], "genre": ["Family"], "image_url": "https://www.bhdstar.vn/wp-content/uploads/2025/05/referenceSchemeHeadOfficeallowPlaceHoldertrueheight700ldapp-8.jpg", "movie_url": "https://www.bhdstar.vn/phim/de-men-cuoc-phieu-luu-toi-xom-lay-loi/"},
{"id": "133793", "title": ["DORAEMON: NOBITA'S ART WORLD TALES"], "age_limit": ["P"], "movie_type": ["Ph\u1ee5 \u0111\u1ec1/L\u1ed3ng ti\u1ebfng"], "format": ["2D"], "genre": ["Family"], "image_url": "https://www.bhdstar.vn/wp-content/uploads/2025/05/referenceSchemeHeadOfficeallowPlaceHoldertrueheight700ldapp-5.jpg", "movie_url": "https://www.bhdstar.vn/phim/doraemon-nobitas-art-world-tales/"},
{"id": "136936", "title": ["LILO &AMP; STITCH"], "age_limit": ["P"], "movie_type": ["Ph\u1ee5 \u0111\u1ec1/L\u1ed3ng ti\u1ebfng"], "format": ["2D"], "genre": ["Family"], "image_url": "https://www.bhdstar.vn/wp-content/uploads/2025/05/referenceSchemeHeadOfficeallowPlaceHoldertrueheight700ldapp-2.png", "movie_url": "https://www.bhdstar.vn/phim/lilo-stitch/"},
{"id": "127526", "title": ["MISSION IMPOSSIBLE: NGHI\u1ec6P B\u00c1O CU\u1ed0I C\u00d9NG"], "age_limit": ["T16"], "movie_type": ["Ph\u1ee5 \u0111\u1ec1"], "format": ["2D"], "genre": ["Action"], "image_url": "https://www.bhdstar.vn/wp-content/uploads/2025/05/referenceSchemeHeadOfficeallowPlaceHoldertrueheight700ldapp-6.jpg", "movie_url": "https://www.bhdstar.vn/phim/mission-impossible-nghiep-bao-cuoi-cung/"},
{"id": "144112", "title": ["THE STONE: BU\u00d4N TH\u1ea6N B\u00c1N TH\u00c1NH"], "age_limit": ["T16"], "movie_type": ["Ph\u1ee5 \u0111\u1ec1"], "format": ["2D"], "genre": ["Action"], "image_url": "https://www.bhdstar.vn/wp-content/uploads/2025/05/referenceSchemeHeadOfficeallowPlaceHoldertrueheight700ldapp-7.jpg", "movie_url": "https://www.bhdstar.vn/phim/the-stone-buon-than-ban-thanh/"},
{"id": "130621", "title": ["N\u0102M M\u01af\u1edcI"], "age_limit": ["T18"], "movie_type": ["Ph\u1ee5 \u0111\u1ec1"], "format": ["2D"], "genre": ["Thriller"], "image_url": "https://www.bhdstar.vn/wp-content/uploads/2025/05/referenceSchemeHeadOfficeallowPlaceHoldertrueheight700ldapp-11.jpg", "movie_url": "https://www.bhdstar.vn/phim/nam-muoi/"},
{"id": "138273", "title": ["YADANG: THE SNITCH: BA M\u1eb6T L\u1eacT K\u00c8O"], "age_limit": ["T18"], "movie_type": ["Ph\u1ee5 \u0111\u1ec1"], "format": ["2D"], "genre": ["Action"], "image_url": "https://www.bhdstar.vn/wp-content/uploads/2025/05/referenceSchemeHeadOfficeallowPlaceHoldertrueheight700ldapp.png", "movie_url": "https://www.bhdstar.vn/phim/yadang-the-snitch-ba-mat-lat-keo/"},
{"id": "141297", "title": ["M\u01afA L\u1eecA: ANH TRAI V\u01af\u1ee2T NG\u00c0N CH\u00d4NG GAI MOVIE"], "age_limit": ["K"], "movie_type": ["Ph\u1ee5 \u0111\u1ec1"], "format": ["2D"], "genre": ["Musical"], "image_url": "https://www.bhdstar.vn/wp-content/uploads/2025/05/referenceSchemeHeadOfficeallowPlaceHoldertrueheight700ldapp-1.jpg", "movie_url": "https://www.bhdstar.vn/phim/mua-lua-anh-trai-vuot-ngan-chong-gai-movie/"},
{"id": "145566", "title": ["BRING HER BACK"], "age_limit": ["T18"], "movie_type": ["Ph\u1ee5 \u0111\u1ec1"], "format": ["2D"], "genre": ["Horror"], "image_url": "https://www.bhdstar.vn/wp-content/uploads/2025/05/referenceSchemeHeadOfficeallowPlaceHoldertrueheight700ldapp-10.jpg", "movie_url": "https://www.bhdstar.vn/phim/bring-her-back/"},
{"id": "130370", "title": ["L\u1eacT M\u1eb6T 8: V\u00d2NG TAY N\u1eaeNG"], "age_limit": ["T13"], "movie_type": ["Ph\u1ee5 \u0111\u1ec1"], "format": ["2D"], "genre": ["Healing"], "image_url": "https://www.bhdstar.vn/wp-content/uploads/2025/04/referenceSchemeHeadOfficeallowPlaceHoldertrueheight700ldapp-7.png", "movie_url": "https://www.bhdstar.vn/phim/lat-mat-8-vong-tay-nang/"},
{"id": "112403", "title": ["TH\u00c1M T\u1eec KI\u00caN: K\u1ef2 \u00c1N KH\u00d4NG \u0110\u1ea6U"], "age_limit": ["T16"], "movie_type": ["Ph\u1ee5 \u0111\u1ec1"], "format": ["2D"], "genre": ["Thriller"], "image_url": "https://www.bhdstar.vn/wp-content/uploads/2025/04/referenceSchemeHeadOfficeallowPlaceHoldertrueheight700ldapp-9.jpg", "movie_url": "https://www.bhdstar.vn/phim/tham-tu-kien/"},
{"id": "136922", "title": ["D\u01af\u1edaI \u0110\u00c1Y H\u1ed2"], "age_limit": ["T18"], "movie_type": ["Ph\u1ee5 \u0111\u1ec1"], "format": ["2D"], "genre": ["Horror"], "image_url": "https://www.bhdstar.vn/wp-content/uploads/2025/05/referenceSchemeHeadOfficeallowPlaceHoldertrueheight700ldapp-6.png", "movie_url": "https://www.bhdstar.vn/phim/duoi-day-ho/"},
{"id": "138275", "title": ["UNTIL DAWN: B\u00cd M\u1eacT KINH HO\u00c0NG"], "age_limit": ["T18"], "movie_type": ["Ph\u1ee5 \u0111\u1ec1"], "format": ["2D"], "genre": ["Horror"], "image_url": "https://www.bhdstar.vn/wp-content/uploads/2025/05/referenceSchemeHeadOfficeallowPlaceHoldertrueheight700ldapp-3.jpg", "movie_url": "https://www.bhdstar.vn/phim/until-dawn-bi-mat-kinh-hoang/"}
]